icetemp/Constants.py
icetemp/InversionMCMCSimulation.py
icetemp/ModelMeasured.py
icetemp/TemperatureModel.py
icetemp/Utilities.py
icetemp/__init__.py
tests/__init__.py
tests/test_ModelMeasured.py
tests/test_TemperatureModel.py
icetemp-0.3.0.dist-info/LICENSE.txt
icetemp-0.3.0.dist-info/METADATA
icetemp-0.3.0.dist-info/WHEEL
icetemp-0.3.0.dist-info/top_level.txt
icetemp-0.3.0.dist-info/RECORD
